Workbook

Sheet 模拟输入
A1: 单次结算模拟
A2: 合同编号 | B2: 合同名称 | C2: 服务对象 | D2: 服务区域 | E2: 合同金额 | F2: 订单编号 | G2: 结算项目 | H2: 结算比例 | I2: 结算金额 | J2: 结算日期 | K2: 一级分账 | O2: 二级分账
K3: 结算单位 | L3: 比例 | M3: 金额 | N3: 补税差 | O3: 分包单位 | P3: 比例 | Q3: 金额 | R3: 施工队 | S3: 比例 | T3: 金额 | U3: 农民工工资 | V3: 补税点 | W3: 补税差
B4: {=VLOOKUP(A4,Sheet1!M:O,{2},FALSE)} -> #N/A | C4: =VLOOKUP(A4,Sheet1!M:Q,4,FALSE) -> #N/A | D4: =VLOOKUP(A4,Sheet1!M:Q,5,FALSE) -> #N/A | E4: =VLOOKUP(A4,Sheet1!M:O,3,FALSE) -> #N/A | I4: =E4*H4 -> #N/A | M4: =_xlfn.IFNA($I$4*L4,"") | Q4: =_xlfn.IFNA($I$4*P4,"") | S4: =_xlfn.IFNA(VLOOKUP(R4,Sheet1!K:L,2,FALSE),"") | T4: =IFERROR($I$4*S4-U4-V4-W4,"") | V4: =U4*0.9 -> 0
M5: =_xlfn.IFNA($I$4*L5,"") | Q5: =_xlfn.IFNA($I$4*P5,"") | S5: =_xlfn.IFNA(VLOOKUP(R5,Sheet1!K:L,2,FALSE),"") | T5: =IFERROR($I$4*S5-U5-V5-W5,"") | V5: =U5*0.9 -> 0
M6: =_xlfn.IFNA($I$4*L6,"") | Q6: =_xlfn.IFNA($I$4*P6,"") | S6: =_xlfn.IFNA(VLOOKUP(R6,Sheet1!K:L,2,FALSE),"") | T6: =IFERROR($I$4*S6-U6-V6-W6,"") | V6: =U6*0.9 -> 0
M7: =_xlfn.IFNA($I$4*L7,"") | Q7: =_xlfn.IFNA($I$4*P7,"") | S7: =_xlfn.IFNA(VLOOKUP(R7,Sheet1!K:L,2,FALSE),"") | T7: =IFERROR($I$4*S7-U7-V7-W7,"") | V7: =U7*0.9 -> 0
M8: =_xlfn.IFNA($I$4*L8,"") | Q8: =_xlfn.IFNA($I$4*P8,"") | S8: =_xlfn.IFNA(VLOOKUP(R8,Sheet1!K:L,2,FALSE),"") | T8: =IFERROR($I$4*S8-U8-V8-W8,"") | V8: =U8*0.9 -> 0
M9: =_xlfn.IFNA($I$4*L9,"") | Q9: =_xlfn.IFNA($I$4*P9,"") | S9: =_xlfn.IFNA(VLOOKUP(R9,Sheet1!K:L,2,FALSE),"") | T9: =IFERROR($I$4*S9-U9-V9-W9,"") | V9: =U9*0.9 -> 0
M10: =_xlfn.IFNA($I$4*L10,"") | Q10: =_xlfn.IFNA($I$4*P10,"") | S10: =_xlfn.IFNA(VLOOKUP(R10,Sheet1!K:L,2,FALSE),"") | T10: =IFERROR($I$4*S10-U10-V10-W10,"") | V10: =U10*0.9 -> 0
M11: =_xlfn.IFNA($I$4*L11,"") | Q11: =_xlfn.IFNA($I$4*P11,"") | S11: =_xlfn.IFNA(VLOOKUP(R11,Sheet1!K:L,2,FALSE),"") | T11: =IFERROR($I$4*S11-U11-V11-W11,"") | V11: =U11*0.9 -> 0

Sheet Sheet1
A1: 单位 | C1: 结算项目 | D1: 金额名称 | E1: 日期名称 | I1: 公司 | J1: 分包公司 | K1: 施工队 | L1: 结算比例 | M1: 合同编号 | N1: 合同名称 | O1: 合同金额 | P1: 服务对象 | Q1: 服务区域 | R1: 结算项目
A2: 公司名称 | B2: 结算对象 | F2: 结算 | I2: 中邮建 | J2: 浩锋 | K2: 广西贵鸿 | L2: 0.8 | M2: CMGX-202200373 | N2: 中国移动广西公司2022年站点接入光缆线路一阶段玉林工程 | O2: 100000 | P2: 广西移动 | Q2: 广西玉林 | R2: 预付款
A3: 中邮建 | B3: 总包商 | C3: 预付款 | D3: 合同金额 | E3: 到账日期 | F3: 结算比例 | I3: 唐贝 | J3: 其他 | K3: 湖南正真 | L3: 0.7 | M3: CMCCTD-GX-202200082 | N3: 中国移动广西分公司2022年通信管道一阶段玉林工程 | O3: 200000 | P3: 陕西移动 | Q3: 广西钦州 | R3: 进度款
A4: 毅和 | B4: 承包商 | C4: 进度款 | D4: 结算金额 | E4: 发票日期 | F4: 结算金额 | I4: 毅和 | K4: 钦州中正 | L4: 0.6 | R4: 安全生产费
A5: 浩锋 | B5: 分包商 | C5: 安全生产费 | D5: 应收金额 | E5: 支付日期 | I5: 沃驰 | K5: 重庆兴瑞 | L5: 0.5 | R5: 审计款
A6: 岩亨 | B6: 施工队 | C6: 审计款 | D6: 应付金额 | R6: 完工款
A7: 中国移动广西公司 | B7: 施工对象 | C7: 完工款 | D7: 已收金额 | R7: 工程款
B8: 农民工 | C8: 工程款 | D8: 已付金额
